{
  "routes": [
    {
      "method": "GET",
      "path": "/exam",
      "handler": "Exam.find",
      "config": {
        "policies": []
      }
    },
    {
      "method": "GET",
      "path": "/exam/count",
      "handler": "Exam.count",
      "config": {
        "policies": []
      }
    },
    {
      "method": "GET",
      "path": "/exam/:_id",
      "handler": "Exam.findOne",
      "config": {
        "policies": []
      }
    },
    {
      "method": "POST",
      "path": "/exam",
      "handler": "Exam.create",
      "config": {
        "policies": []
      }
    },
    {
      "method": "PUT",
      "path": "/exam/:_id",
      "handler": "Exam.update",
      "config": {
        "policies": []
      }
    },
    {
      "method": "DELETE",
      "path": "/exam/:_id",
      "handler": "Exam.destroy",
      "config": {
        "policies": []
      }
    }
  ]
}